cinderdiags/__init__.py
cinderdiags/access.py
cinderdiags/conf_reader.py
cinderdiags/constant.py
cinderdiags/hp3par_testclient.py
cinderdiags/hp3par_wsapi_checks.py
cinderdiags/hpe3par_testclient.py
cinderdiags/hpe3par_wsapi_checks.py
cinderdiags/lun_stats.py
cinderdiags/main.py
cinderdiags/options.py
cinderdiags/pkg_checks.py
cinderdiags/software.py
cinderdiags/ssh_client.py
cinderdiags/volume_paths.py
cinderdiags-2.4.1.dist-info/DESCRIPTION.rst
cinderdiags-2.4.1.dist-info/METADATA
cinderdiags-2.4.1.dist-info/RECORD
cinderdiags-2.4.1.dist-info/WHEEL
cinderdiags-2.4.1.dist-info/entry_points.txt
cinderdiags-2.4.1.dist-info/metadata.json
cinderdiags-2.4.1.dist-info/pbr.json
cinderdiags-2.4.1.dist-info/top_level.txt
