Metadata-Version: 2.0
Name: cinderdiags
Version: 2.4.1
Summary: Cinder Diagnostics CLI
Home-page: http://github.com/hp-storage/diags
Author: HPE Storage Cloud Team
Author-email: richard.hagarty@hpe.com
License: UNKNOWN
Platform: UNKNOWN
Classifier: Environment :: OpenStack
Classifier: Intended Audience :: Information Technology
Classifier: Intended Audience :: System Administrators
Classifier: License :: OSI Approved :: Apache Software License
Classifier: Operating System :: POSIX :: Linux
Classifier: Programming Language :: Python
Classifier: Programming Language :: Python :: 2
Classifier: Programming Language :: Python :: 2.7
Classifier: Programming Language :: Python :: 2.6
Classifier: Programming Language :: Python :: 3
Classifier: Programming Language :: Python :: 3.3
Classifier: Programming Language :: Python :: 3.4
Requires-Dist: pbr (>=1.8)
Requires-Dist: python-3parclient (>=4.0)
Requires-Dist: python-cinderclient (>=1.8.0)
Requires-Dist: python-lefthandclient (>=2.0)
